README.md
nbresnote.py
setup.py
bin/nbresnote
nbresnote.egg-info/PKG-INFO
nbresnote.egg-info/SOURCES.txt
nbresnote.egg-info/dependency_links.txt
nbresnote.egg-info/top_level.txt