Metadata-Version: 1.0
Name: nbresnote
Version: 0.1.3
Summary: auto research note conversion
Home-page: UNKNOWN
Author: jhjung
Author-email: jhjung@uos.ac.kr
License: UNKNOWN
Platform: UNKNOWN
